{
  "useAsyncTasks": "useAsyncTasks",
  "useClipboard": "useClipboard",
  "useConfirm": "useConfirm",
  "useDebounce": "useDebounce",
  "useDeepCompareEffect": "useDeepCompareEffect",
  "useDelayFlag": "useDelayFlag",
  "useDetectDevice": "useDetectDevice",
  "useEventListener": "useEventListener",
  "useGeolocation": "useGeolocation",
  "useHover": "useHover",
  "useIntersectionObserver": "useIntersectionObserver",
  "useInterval": "useInterval",
  "useKeyCombination": "useKeyCombination",
  "useKeyDown": "useKeyDown",
  "useLocalStorage": "useLocalStorage",
  "useLongPress": "useLongPress",
  "useMockData": "useMockData",
  "useMousePosition": "useMousePosition",
  "useOnlineStatus": "useOnlineStatus",
  "useOutsideClick": "useOutsideClick",
  "usePermission": "usePermission",
  "usePrefersColorScheme": "usePrefersColorScheme",
  "usePreventCopy": "usePreventCopy",
  "useScrollLock": "useScrollLock",
  "useScrollY": "useScrollY",
  "useSound": "useSound",
  "useTimer": "useTimer",
  "useToggle": "useToggle",
  "useTranslation": "useTranslation",
  "useUnmountEffect": "useUnmountEffect",
  "useWorker": "useWorker",
  "_template": {
    "display": "hidden"
  }
}
